[
  {
    "id": "dd5fbe4e-4baf-4f3e-b3c4-3d14d3476af7",
    "sme_id": "4137b2e8-dcd4-4300-a109-343cff5bcc27",
    "sme_name": "TECHNO FOOD BERKANE",
    "need_id": "need-001",
    "need_title": "Transport de conteneurs — zone franche Nador West Med — 3 camions minimum",
    "message": "",
    "status": "rejected",
    "score": 16,
    "applied_at": "2026-03-13T02:24:04.803435",
    "decided_at": "2026-03-13T02:59:38.799612",
    "decided_by": "port_user"
  },
  {
    "id": "d475790e-fbe1-4d0a-8e9e-d580cdd15be6",
    "sme_id": "b2a48ba0-61fd-48fd-918a-778995f202b3",
    "sme_name": "TECHNO FOOD BERKANE",
    "need_id": "need-001",
    "need_title": "Transport de conteneurs — zone franche Nador West Med — 3 camions minimum",
    "message": "",
    "status": "rejected",
    "score": 16,
    "applied_at": "2026-03-13T02:26:47.836125",
    "decided_at": "2026-03-13T02:59:37.927571",
    "decided_by": "port_user"
  },
  {
    "id": "08ea41b3-6005-4fb0-ac93-c4815473ae10",
    "sme_id": "sme-003",
    "sme_name": "NADOR LOGISTICS SARL",
    "need_id": "need-001",
    "need_title": "Transport de conteneurs — zone franche Nador West Med — 3 camions minimum",
    "message": "Invitation du port Nador West Med — score IA : 85/100",
    "status": "accepted",
    "score": 85,
    "applied_at": "2026-03-13T02:35:05.126819",
    "decided_at": "2026-03-13T02:35:59.361064",
    "decided_by": "port_user"
  },
  {
    "id": "75769169-4c81-44be-939d-e2781f29818b",
    "sme_id": "sme-001",
    "sme_name": "TRANSORIENT SARL",
    "need_id": "need-002",
    "need_title": "Maintenance industrielle des équipements de manutention portuaire — Zone industrielle Berkane",
    "message": "",
    "status": "pending",
    "score": 57,
    "applied_at": "2026-03-13T02:53:06.656759",
    "decided_at": null,
    "decided_by": ""
  },
  {
    "id": "92493100-b4d2-4a89-a93d-d9d4a16d1ff8",
    "sme_id": "sme-001",
    "sme_name": "TRANSORIENT SARL",
    "need_id": "need-003",
    "need_title": "Restauration collective industrielle — 200 repas halal/jour pour les travailleurs du port Nador West Med",
    "message": "test",
    "status": "pending",
    "score": 33,
    "applied_at": "2026-03-13T02:53:55.024663",
    "decided_at": null,
    "decided_by": ""
  }
]